Metadata-Version: 2.1
Name: pynta-flow
Version: 1.1.0
Summary: An automated workflow for reaction path exploration on metallic surfaces
Home-page: https://zadorlab.github.io/pynta
Author: Maciej Gierada, Eric D. Hermes, David H. Bross
Author-email: maciek.gierada@gmail.com
License: GPL-3.0
Project-URL: Source, https://github.com/zadorlab/pynta
Project-URL: Documentation, https://zadorlab.github.io/pynta
Keywords: surface,catalysis,chemistry,physics,hpc,workflow,automation
Platform: UNKNOWN
Classifier: Development Status :: 4 - Beta
Classifier: Intended Audience :: Developers
Classifier: Intended Audience :: Science/Research
Classifier: Topic :: Scientific/Engineering :: Chemistry
Classifier: Topic :: Scientific/Engineering :: Mathematics
Classifier: Topic :: Scientific/Engineering :: Physics
Classifier: Natural Language :: English
Classifier: Operating System :: OS Independent
Classifier: License :: OSI Approved :: GNU General Public License v3 (GPLv3)
Classifier: Programming Language :: Python :: 3.6
Classifier: Programming Language :: Python :: 3.7
Classifier: Programming Language :: Python :: 3.8
Requires-Python: >=3.6
Requires-Dist: balsam-flow (==0.3.8)
Requires-Dist: matplotlib (<3.2)
Requires-Dist: spglib (==1.14.1.post0)
Requires-Dist: networkx (<2.4)
Requires-Dist: ase (==3.19.0)
Requires-Dist: scipy (<=1.6,>=1.3.1)
Requires-Dist: numpy (==1.18.1)
Requires-Dist: PyYAML (==5.3.1)
Requires-Dist: Sella (>=1.0.3)
